MANIFEST.in
README.md
requirements.txt
setup.py
parser_engine/__init__.py
parser_engine/config.py
parser_engine/decorator.py
parser_engine/itemclassloader.py
parser_engine/log.py
parser_engine/parser.py
parser_engine/patch.py
parser_engine/request.py
parser_engine/singleton.py
parser_engine/spider.py
parser_engine/template.py
parser_engine/utils.py
parser_engine.egg-info/PKG-INFO
parser_engine.egg-info/SOURCES.txt
parser_engine.egg-info/dependency_links.txt
parser_engine.egg-info/requires.txt
parser_engine.egg-info/top_level.txt
parser_engine.egg-info/zip-safe
parser_engine/clue/__init__.py
parser_engine/clue/constants.py
parser_engine/clue/items.py
parser_engine/clue/middlewares.py
parser_engine/clue/models.py
parser_engine/clue/pipelines.py
parser_engine/clue/spider.py
parser_engine/templates/parser_engine.json
tests/__init__.py
tests/parser_test.py
tests/template_test.py
tests/utils_test.py